odoo8_addon_l10n_it_ddt-8.0.1.0.2-py2.7-nspkg.pth
odoo8_addon_l10n_it_ddt-8.0.1.0.2.dist-info/METADATA
odoo8_addon_l10n_it_ddt-8.0.1.0.2.dist-info/RECORD
odoo8_addon_l10n_it_ddt-8.0.1.0.2.dist-info/WHEEL
odoo8_addon_l10n_it_ddt-8.0.1.0.2.dist-info/namespace_packages.txt
odoo8_addon_l10n_it_ddt-8.0.1.0.2.dist-info/top_level.txt
odoo_addons/l10n_it_ddt/README.rst
odoo_addons/l10n_it_ddt/__init__.py
odoo_addons/l10n_it_ddt/__openerp__.py
odoo_addons/l10n_it_ddt/data/ddt_data.xml
odoo_addons/l10n_it_ddt/i18n/es.po
odoo_addons/l10n_it_ddt/i18n/it.po
odoo_addons/l10n_it_ddt/i18n/l10n_it_ddt.pot
odoo_addons/l10n_it_ddt/i18n/sl.po
odoo_addons/l10n_it_ddt/models/__init__.py
odoo_addons/l10n_it_ddt/models/account.py
odoo_addons/l10n_it_ddt/models/partner.py
odoo_addons/l10n_it_ddt/models/sale.py
odoo_addons/l10n_it_ddt/models/stock.py
odoo_addons/l10n_it_ddt/models/stock_picking_package_preparation.py
odoo_addons/l10n_it_ddt/security/ir.model.access.csv
odoo_addons/l10n_it_ddt/security/security.xml
odoo_addons/l10n_it_ddt/static/description/icon.png
odoo_addons/l10n_it_ddt/tests/__init__.py
odoo_addons/l10n_it_ddt/tests/test_ddt.py
odoo_addons/l10n_it_ddt/views/account.xml
odoo_addons/l10n_it_ddt/views/partner.xml
odoo_addons/l10n_it_ddt/views/report_ddt.xml
odoo_addons/l10n_it_ddt/views/sale.xml
odoo_addons/l10n_it_ddt/views/stock_picking_package_preparation.xml
odoo_addons/l10n_it_ddt/wizard/__init__.py
odoo_addons/l10n_it_ddt/wizard/add_picking_to_ddt.py
odoo_addons/l10n_it_ddt/wizard/add_picking_to_ddt.xml
odoo_addons/l10n_it_ddt/wizard/ddt_create_invoice.py
odoo_addons/l10n_it_ddt/wizard/ddt_create_invoice.xml
odoo_addons/l10n_it_ddt/wizard/ddt_from_picking.py
odoo_addons/l10n_it_ddt/wizard/ddt_from_picking.xml
