Metadata-Version: 2.1
Name: odoo8-addon-l10n-it-ddt
Version: 8.0.1.0.2
Summary: Documento di Trasporto
Home-page: http://www.odoo-italia.org/
Author: Davide Corio, Odoo Community Association (OCA),Agile Business Group, Francesco Apruzzese, Apulia Software
Author-email: support@odoo-community.org
License: AGPL-3
Platform: UNKNOWN
Classifier: Programming Language :: Python
Classifier: Framework :: Odoo
Classifier: License :: OSI Approved :: GNU Affero General Public License v3
Requires-Python: ~=2.7
Requires-Dist: odoo8-addon-stock-picking-package-preparation-line
Requires-Dist: odoo (<9.0a,>=8.0a)
